[
  {
    "label": "De quelle couleur-s sont les pandas ?",
    "quizId": 14,
    "id": 1587807107215
  },
  {
    "label": "Combien y a t-il de pandas dans le monde actuel ?",
    "quizId": 14,
    "id": 1587807401252
  },
  {
    "label": "Les pandas peuvent-ils parler ?",
    "quizId": 14,
    "id": 1587807529018
  },
  {
    "label": "Doit-on aimer les pandas ?",
    "quizId": 14,
    "id": 1587807633789
  },
  {
    "label": "Quel est le facteur de décroissance de la puissance en fonction du rayon R ?",
    "quizId": 19,
    "id": 1587808617173
  },
  {
    "label": "Dans quel anime un lycéen voit son bras droit changer de forme ?",
    "quizId": 20,
    "id": 1587816081070
  },
  {
    "label": "Qui est Kakashi ?",
    "quizId": 20,
    "id": 1587816081458
  },
  {
    "label": "Quel est le pouvoir de Subaru ?",
    "quizId": 20,
    "id": 1587816081754
  },
  {
    "label": "Le reigne de Cléopatre est plus proche de 2020 que de la création des grandes pyramides",
    "quizId": 21,
    "id": 1587816703359
  },
  {
    "label": "Hitler était en réalité chauve",
    "quizId": 21,
    "id": 1587816772470
  },
  {
    "label": "Une grande partie des forces militaires africaines travaillant pour la France se sont faites fusillées gratuitement après la libération",
    "quizId": 21,
    "id": 1587816907829
  },
  {
    "label": "Napoléon n'était pas si petit, il mesurait en réalité plus de 1,70m",
    "quizId": 21,
    "id": 1587817031727
  },
  {
    "label": "Quelle est la plus grande puissance sur Terre ?",
    "quizId": 22,
    "id": 1587817285020
  },
  {
    "label": "Comment appelle-t-on un cosmonaute de nationalité japonaise ?",
    "quizId": 22,
    "id": 1587817285169
  },
  {
    "label": "J'avais deux fois l'âge de mon fils il y a cinq ans, et j'aurai trois fois son age dans vingt ans. Quel est mon âge ?",
    "quizId": 22,
    "id": 1587817286251
  },
  {
    "label": "Êtes vous satisfais de ce quiz ?",
    "quizId": 23,
    "id": 1588063465804
  }
]